youtubepafy/__init__.py
youtubepafy/backend_internal.py
youtubepafy/backend_shared.py
youtubepafy/backend_youtube_dl.py
youtubepafy/channel.py
youtubepafy/g.py
youtubepafy/jsinterp.py
youtubepafy/playlist.py
youtubepafy/util.py
youtubepafy/version.py
youtubepafy/youtubepafy.py
youtubepafy-0.5.5.dist-info/LICENSE
youtubepafy-0.5.5.dist-info/METADATA
youtubepafy-0.5.5.dist-info/WHEEL
youtubepafy-0.5.5.dist-info/top_level.txt
youtubepafy-0.5.5.dist-info/RECORD
