Metadata-Version: 2.1
Name: youtubepafy
Version: 0.5.5
Summary: Retrieve YouTube content and metadata
Home-page: https://github.com/hetsaraiya/youtubepafy
Download-URL: https://github.com/hetsaraiya/youtubepafy/tags
Author: Het Saraiya
Author-email: hetsaraiya06@gmail.com
License: LGPLv3
Keywords: youtubepafy,API,YouTube,youtube,download,video,Het Saraiya,hetsaraiya
Classifier: License :: OSI Approved :: GNU Lesser General Public License v3 (LGPLv3)
Classifier: Operating System :: POSIX :: Linux
Classifier: Operating System :: MacOS
Classifier: Operating System :: MacOS :: MacOS 9
Classifier: Operating System :: MacOS :: MacOS X
Classifier: Operating System :: Microsoft
Classifier: Operating System :: Microsoft :: Windows :: Windows 7
Classifier: Operating System :: Microsoft :: Windows :: Windows XP
Classifier: Programming Language :: Python
Classifier: Programming Language :: Python :: 2
Classifier: Programming Language :: Python :: 2.6
Classifier: Programming Language :: Python :: 2.7
Classifier: Programming Language :: Python :: 3
Classifier: Programming Language :: Python :: 3.3
Classifier: Programming Language :: Python :: 3.4
Classifier: Intended Audience :: Developers
Classifier: Development Status :: 5 - Production/Stable
Classifier: Topic :: Multimedia :: Sound/Audio :: Capture/Recording
Classifier: Topic :: Utilities
Classifier: Topic :: Multimedia :: Video
Classifier: Topic :: Internet :: WWW/HTTP
License-File: LICENSE
Requires-Dist: yt-dlp
Provides-Extra: youtube-dl-backend
Requires-Dist: youtube-dl; extra == "youtube-dl-backend"
